embyupdater/__init__.py
embyupdater/__main__.py
embyupdater/version.py
emby_updater-0.8.4.dist-info/LICENSE
emby_updater-0.8.4.dist-info/METADATA
emby_updater-0.8.4.dist-info/WHEEL
emby_updater-0.8.4.dist-info/entry_points.txt
emby_updater-0.8.4.dist-info/top_level.txt
emby_updater-0.8.4.dist-info/RECORD
