Metadata-Version: 2.1
Name: emby-updater
Version: 0.8.4
Summary: A little tool to keep your emby media server up to date.
Home-page: https://github.com/shokinn/emby-updater
Author: Philip Henning
Author-email: mail@philip-henning.com
License: MIT
Keywords: emby,updater,ubuntu
Classifier: Development Status :: 4 - Beta
Classifier: Environment :: Console
Classifier: Intended Audience :: System Administrators
Classifier: License :: OSI Approved :: MIT License
Classifier: Natural Language :: English
Classifier: Operating System :: POSIX :: Linux
Classifier: Programming Language :: Python :: 3
Classifier: Programming Language :: Python :: 3.6
Classifier: Programming Language :: Python :: 3.7
Classifier: Programming Language :: Python :: 3.8
Classifier: Programming Language :: Python :: 3 :: Only
Classifier: Topic :: System :: Installation/Setup
Classifier: Topic :: System :: Software Distribution
Classifier: Topic :: System :: Systems Administration
Classifier: Topic :: Utilities
Requires-Python: ~=3.6
License-File: LICENSE
Requires-Dist: requests (~=2.20)
